splitlog/__init__.py
splitlog/__main__.py
splitlog/outputfolder.py
splitlog-4.1.1.dist-info/METADATA
splitlog-4.1.1.dist-info/WHEEL
splitlog-4.1.1.dist-info/entry_points.txt
splitlog-4.1.1.dist-info/licenses/LICENSE
splitlog-4.1.1.dist-info/RECORD
