Metadata-Version: 2.4
Name: splitlog
Version: 4.1.1
Summary: Utility to split aggregated logs from Apache Hadoop Yarn applications into a folder hierarchy
License-Expression: MIT
License-File: LICENSE
Author: Sebastian Klemke
Author-email: pypi@nerdheim.de
Requires-Python: >=3.11, <4.0
Classifier: Development Status :: 5 - Production/Stable
Classifier: Environment :: Console
Classifier: Intended Audience :: Developers
Classifier: Operating System :: OS Independent
Classifier: Programming Language :: Python :: 3 :: Only
Classifier: Topic :: System :: Distributed Computing
Classifier: Topic :: System :: Logging
Classifier: Topic :: Utilities
Requires-Dist: python-dateutil (>=2.9.0,<3.0.0)
Requires-Dist: pytz (>=2025.2)
Project-URL: Bug Tracker, https://github.com/splitlog/splitlog/issues
Project-URL: Repository, https://github.com/splitlog/splitlog.git
